pychu/__init__.py
pychu/_dict_utils.py
pychu/_types.py
pychu/args.py
pychu/env.py
pychu/json.py
pychu/toml.py
pychu/yaml.py
pychu-1.0.1.dist-info/LICENSE
pychu-1.0.1.dist-info/METADATA
pychu-1.0.1.dist-info/WHEEL
pychu-1.0.1.dist-info/top_level.txt
pychu-1.0.1.dist-info/RECORD
