Metadata-Version: 2.1
Name: pychu
Version: 1.0.1
Summary: Layered configuration powered by Pydantic
Home-page: https://github.com/doom/pychu
Author: Clément Doumergue
Author-email: clement.doumergue@etna.io
License: UNKNOWN
Platform: UNKNOWN
Classifier: Programming Language :: Python :: 3
Classifier: License :: OSI Approved :: MIT License
Classifier: Operating System :: OS Independent
Requires-Dist: pydantic (<2.*,>=1.7.3)
Provides-Extra: toml
Requires-Dist: toml (~=0.10.2) ; extra == 'toml'
Provides-Extra: yaml
Requires-Dist: PyYAML (~=5.3.1) ; extra == 'yaml'
